bonos/__init__.py
bonos/flujos.py
bonos/optimizacion.py
bonos/riesgo.py
bonos/sensibilidad.py
bonos/simulacion.py
bonos/tasas.py
bonos/valuacion.py
bonos/visualizacion.py
BONO-1.1.4.dist-info/LICENSE
BONO-1.1.4.dist-info/METADATA
BONO-1.1.4.dist-info/WHEEL
BONO-1.1.4.dist-info/top_level.txt
BONO-1.1.4.dist-info/RECORD
