Metadata-Version: 2.1
Name: BONO
Version: 1.1.4
Summary: Librería para análisis y cálculos de bonos financieros
Home-page: https://github.com/LuisHCalderon
Author: Luis Humberto Calderon Baldeón
Author-email: luis.calderon.b@uni.pe
License: MIT
Classifier: Programming Language :: Python :: 3
Classifier: License :: OSI Approved :: MIT License
Classifier: Operating System :: OS Independent
Requires-Python: >=3.7
License-File: LICENSE
Requires-Dist: numpy>=1.21.0
Requires-Dist: matplotlib>=3.5.0
